LICENSE
README.md
pyproject.toml
setup.py
graphormer_pretrained/__init__.py
graphormer_pretrained/_version.py
graphormer_pretrained/embeddings.py
graphormer_pretrained.egg-info/PKG-INFO
graphormer_pretrained.egg-info/SOURCES.txt
graphormer_pretrained.egg-info/dependency_links.txt
graphormer_pretrained.egg-info/not-zip-safe
graphormer_pretrained.egg-info/requires.txt
graphormer_pretrained.egg-info/top_level.txt
graphormer_pretrained/criterions/__init__.py
graphormer_pretrained/criterions/binary_logloss.py
graphormer_pretrained/criterions/l1_loss.py
graphormer_pretrained/criterions/mae_deltapos.py
graphormer_pretrained/criterions/multiclass_cross_entropy.py
graphormer_pretrained/data/__init__.py
graphormer_pretrained/data/algos.c
graphormer_pretrained/data/algos.pyx
graphormer_pretrained/data/collator.py
graphormer_pretrained/data/dataset.py
graphormer_pretrained/data/wrapper.py
graphormer_pretrained/data/ogb_datasets/__init__.py
graphormer_pretrained/data/ogb_datasets/ogb_dataset_lookup_table.py
graphormer_pretrained/data/pyg_datasets/__init__.py
graphormer_pretrained/data/pyg_datasets/pyg_dataset.py
graphormer_pretrained/data/pyg_datasets/pyg_dataset_lookup_table.py
graphormer_pretrained/data/smiles_dataset/__init__.py
graphormer_pretrained/data/smiles_dataset/smiles_dataset.py
graphormer_pretrained/evaluate/__init__.py
graphormer_pretrained/evaluate/evaluate.py
graphormer_pretrained/models/__init__.py
graphormer_pretrained/models/graphormer.py
graphormer_pretrained/models/graphormer_3d.py
graphormer_pretrained/modules/__init__.py
graphormer_pretrained/modules/graphormer_graph_encoder.py
graphormer_pretrained/modules/graphormer_graph_encoder_layer.py
graphormer_pretrained/modules/graphormer_layers.py
graphormer_pretrained/modules/multihead_attention.py
graphormer_pretrained/tasks/__init__.py
graphormer_pretrained/tasks/graph_prediction.py
graphormer_pretrained/tasks/is2re.py
graphormer_pretrained/utils/__init__.py
graphormer_pretrained/utils/amp_optimizer.py
graphormer_pretrained/utils/common.py
graphormer_pretrained/utils/loader.py
tests/test_embeddings.py