Metadata-Version: 2.1
Name: graphormer-pretrained
Version: 0.2.3
Summary: Packaging of Graphormer is a deep learning package by Microsoft that allows researchers and developers to train custom models for molecule modeling tasks.
Author-email: Emmanuel Noutahi <emmanuel@valencediscovery.com>
License: MIT
Project-URL: Source Code, https://github.com/maclandrol/graphormer-pretrained
Project-URL: Bug Tracker, https://github.com/maclandrol/graphormer-pretrained/issues
Requires-Python: >=3.8
License-File: LICENSE
